{"oid": "st_2002-12-18", "hafta": 79, "buyukIkramiyeKazananIl": "", "cekilisTarihi": "18/12/2002", "cekilisTuru": "SANS_TOPU", "rakamlar": "02#05#06#11#34#07", "rakamlarNumaraSirasi": "2 - 5 - 6 - 11 - 34 - <b>07</b>", "devretti": true, "devirSayisi": 0, "bilenKisiler": [{"oid": "st_2002-12-18_51", "kisiBasinaDusenIkramiye": 196215.95, "kisiSayisi": 2, "tur": "$5_1_BILEN"}, {"oid": "st_2002-12-18_5", "kisiBasinaDusenIkramiye": 3019.85, "kisiSayisi": 20, "tur": "$5_BILEN"}, {"oid": "st_2002-12-18_41", "kisiBasinaDusenIkramiye": 120.35, "kisiSayisi": 503, "tur": "$4_1_BILEN"}, {"oid": "st_2002-12-18_4", "kisiBasinaDusenIkramiye": 15.6, "kisiSayisi": 5795, "tur": "$4_BILEN"}, {"oid": "st_2002-12-18_31", "kisiBasinaDusenIkramiye": 4.5, "kisiSayisi": 17498, "tur": "$3_1_BILEN"}, {"oid": "st_2002-12-18_3", "kisiBasinaDusenIkramiye": 1.1, "kisiSayisi": 204720, "tur": "$3_BILEN"}, {"oid": "st_2002-12-18_2", "kisiBasinaDusenIkramiye": 1.4, "kisiSayisi": 180692, "tur": "$2_1_BILEN"}, {"oid": "st_2002-12-18_11", "kisiBasinaDusenIkramiye": 0.55, "kisiSayisi": 633968, "tur": "$1_1_BILEN"}], "buyukIkrKazananIlIlceler": []}