{"oid": "st_2003-04-02", "hafta": 94, "buyukIkramiyeKazananIl": "", "cekilisTarihi": "02/04/2003", "cekilisTuru": "SANS_TOPU", "rakamlar": "12#13#15#19#27#08", "rakamlarNumaraSirasi": "12 - 13 - 15 - 19 - 27 - <b>08</b>", "devretti": true, "devirSayisi": 0, "bilenKisiler": [{"oid": "st_2003-04-02_51", "kisiBasinaDusenIkramiye": 134920.7, "kisiSayisi": 3, "tur": "$5_1_BILEN"}, {"oid": "st_2003-04-02_5", "kisiBasinaDusenIkramiye": 2224.65, "kisiSayisi": 28, "tur": "$5_BILEN"}, {"oid": "st_2003-04-02_41", "kisiBasinaDusenIkramiye": 138.6, "kisiSayisi": 450, "tur": "$4_1_BILEN"}, {"oid": "st_2003-04-02_4", "kisiBasinaDusenIkramiye": 13.9, "kisiSayisi": 6723, "tur": "$4_BILEN"}, {"oid": "st_2003-04-02_31", "kisiBasinaDusenIkramiye": 5.85, "kisiSayisi": 13552, "tur": "$3_1_BILEN"}, {"oid": "st_2003-04-02_3", "kisiBasinaDusenIkramiye": 1.15, "kisiSayisi": 203798, "tur": "$3_BILEN"}, {"oid": "st_2003-04-02_2", "kisiBasinaDusenIkramiye": 2, "kisiSayisi": 123934, "tur": "$2_1_BILEN"}, {"oid": "st_2003-04-02_11", "kisiBasinaDusenIkramiye": 0.95, "kisiSayisi": 391989, "tur": "$1_1_BILEN"}], "buyukIkrKazananIlIlceler": []}