{"oid": "st_2005-03-02", "hafta": 194, "buyukIkramiyeKazananIl": "", "cekilisTarihi": "02/03/2005", "cekilisTuru": "SANS_TOPU", "rakamlar": "01#19#20#21#28#14", "rakamlarNumaraSirasi": "1 - 19 - 20 - 21 - 28 - <b>14</b>", "devretti": true, "devirSayisi": 0, "bilenKisiler": [{"oid": "st_2005-03-02_51", "kisiBasinaDusenIkramiye": 210803.1, "kisiSayisi": 2, "tur": "$5_1_BILEN"}, {"oid": "st_2005-03-02_5", "kisiBasinaDusenIkramiye": 1615.6, "kisiSayisi": 27, "tur": "$5_BILEN"}, {"oid": "st_2005-03-02_41", "kisiBasinaDusenIkramiye": 269.2, "kisiSayisi": 216, "tur": "$4_1_BILEN"}, {"oid": "st_2005-03-02_4", "kisiBasinaDusenIkramiye": 19.55, "kisiSayisi": 2987, "tur": "$4_BILEN"}, {"oid": "st_2005-03-02_31", "kisiBasinaDusenIkramiye": 13.05, "kisiSayisi": 5864, "tur": "$3_1_BILEN"}, {"oid": "st_2005-03-02_3", "kisiBasinaDusenIkramiye": 2.4, "kisiSayisi": 89732, "tur": "$3_BILEN"}, {"oid": "st_2005-03-02_2", "kisiBasinaDusenIkramiye": 3.95, "kisiSayisi": 55513, "tur": "$2_1_BILEN"}, {"oid": "st_2005-03-02_11", "kisiBasinaDusenIkramiye": 1.9, "kisiSayisi": 189938, "tur": "$1_1_BILEN"}], "buyukIkrKazananIlIlceler": []}