{"oid": "st_2006-11-22", "hafta": 284, "buyukIkramiyeKazananIl": "", "cekilisTarihi": "22/11/2006", "cekilisTuru": "SANS_TOPU", "rakamlar": "01#03#09#11#17#06", "rakamlarNumaraSirasi": "1 - 3 - 9 - 11 - 17 - <b>06</b>", "devretti": true, "devirSayisi": 0, "bilenKisiler": [{"oid": "st_2006-11-22_51", "kisiBasinaDusenIkramiye": 559284.6, "kisiSayisi": 1, "tur": "$5_1_BILEN"}, {"oid": "st_2006-11-22_5", "kisiBasinaDusenIkramiye": 1155.55, "kisiSayisi": 44, "tur": "$5_BILEN"}, {"oid": "st_2006-11-22_41", "kisiBasinaDusenIkramiye": 137.5, "kisiSayisi": 371, "tur": "$4_1_BILEN"}, {"oid": "st_2006-11-22_4", "kisiBasinaDusenIkramiye": 13.25, "kisiSayisi": 5113, "tur": "$4_BILEN"}, {"oid": "st_2006-11-22_31", "kisiBasinaDusenIkramiye": 8.35, "kisiSayisi": 10909, "tur": "$3_1_BILEN"}, {"oid": "st_2006-11-22_3", "kisiBasinaDusenIkramiye": 1.65, "kisiSayisi": 140906, "tur": "$3_BILEN"}, {"oid": "st_2006-11-22_2", "kisiBasinaDusenIkramiye": 2.5, "kisiSayisi": 94293, "tur": "$2_1_BILEN"}, {"oid": "st_2006-11-22_11", "kisiBasinaDusenIkramiye": 1.4, "kisiSayisi": 290422, "tur": "$1_1_BILEN"}], "buyukIkrKazananIlIlceler": []}