{"oid": "st_2012-11-21", "hafta": 597, "buyukIkramiyeKazananIl": "", "cekilisTarihi": "21/11/2012", "cekilisTuru": "SANS_TOPU", "rakamlar": "04#09#27#28#33#06", "rakamlarNumaraSirasi": "4 - 9 - 27 - 28 - 33 - <b>06</b>", "devretti": true, "bilenKisiler": [{"oid": "st_2012-11-21_51", "kisiBasinaDusenIkramiye": 619949.28, "kisiSayisi": 0, "tur": "$5_1_BILEN"}, {"oid": "st_2012-11-21_5", "kisiBasinaDusenIkramiye": 4133.2, "kisiSayisi": 15, "tur": "$5_BILEN"}, {"oid": "st_2012-11-21_41", "kisiBasinaDusenIkramiye": 262.1, "kisiSayisi": 237, "tur": "$4_1_BILEN"}, {"oid": "st_2012-11-21_4", "kisiBasinaDusenIkramiye": 27.7, "kisiSayisi": 2984, "tur": "$4_BILEN"}, {"oid": "st_2012-11-21_31", "kisiBasinaDusenIkramiye": 14.3, "kisiSayisi": 7354, "tur": "$3_1_BILEN"}, {"oid": "st_2012-11-21_3", "kisiBasinaDusenIkramiye": 3.2, "kisiSayisi": 90643, "tur": "$3_BILEN"}, {"oid": "st_2012-11-21_2", "kisiBasinaDusenIkramiye": 4.3, "kisiSayisi": 69043, "tur": "$2_1_BILEN"}, {"oid": "st_2012-11-21_11", "kisiBasinaDusenIkramiye": 2.35, "kisiSayisi": 233051, "tur": "$1_1_BILEN"}], "buyukIkrKazananIlIlceler": []}