{"oid": "st_2012-10-24", "hafta": 593, "buyukIkramiyeKazananIl": "", "cekilisTarihi": "24/10/2012", "cekilisTuru": "SANS_TOPU", "rakamlar": "03#06#10#25#27#09", "rakamlarNumaraSirasi": "3 - 6 - 10 - 25 - 27 - <b>09</b>", "devretti": false, "bilenKisiler": [{"oid": "st_2012-10-24_51", "kisiBasinaDusenIkramiye": 598879.85, "kisiSayisi": 1, "tur": "$5_1_BILEN"}, {"oid": "st_2012-10-24_5", "kisiBasinaDusenIkramiye": 2218.1, "kisiSayisi": 27, "tur": "$5_BILEN"}, {"oid": "st_2012-10-24_41", "kisiBasinaDusenIkramiye": 223.85, "kisiSayisi": 268, "tur": "$4_1_BILEN"}, {"oid": "st_2012-10-24_4", "kisiBasinaDusenIkramiye": 23.85, "kisiSayisi": 3358, "tur": "$4_BILEN"}, {"oid": "st_2012-10-24_31", "kisiBasinaDusenIkramiye": 14, "kisiSayisi": 7420, "tur": "$3_1_BILEN"}, {"oid": "st_2012-10-24_3", "kisiBasinaDusenIkramiye": 2.8, "kisiSayisi": 98814, "tur": "$3_BILEN"}, {"oid": "st_2012-10-24_2", "kisiBasinaDusenIkramiye": 4.15, "kisiSayisi": 67067, "tur": "$2_1_BILEN"}, {"oid": "st_2012-10-24_11", "kisiBasinaDusenIkramiye": 2.5, "kisiSayisi": 215411, "tur": "$1_1_BILEN"}], "buyukIkrKazananIlIlceler": [{"il": "01", "ilView": "ADANA", "ilce": "00117", "ilceView": "Y\u00dcRE\u011e\u0130R"}]}