{"oid": "64ijs4hmav0flo00", "hafta": 642, "buyukIkramiyeKazananIl": "", "cekilisTarihi": "02/10/2013", "cekilisTuru": "SANS_TOPU", "rakamlar": "14#31#25#20#03#06", "rakamlarNumaraSirasi": "03 - 14 - 20 - 25 - 31 - <b>06</b>", "devretti": false, "devirSayisi": 0, "bilenKisiler": [{"oid": "641bplhmav0fll07", "kisiBasinaDusenIkramiye": 2.4, "kisiSayisi": 222212, "tur": "$1_1_BILEN"}, {"oid": "641bplhmav0fll06", "kisiBasinaDusenIkramiye": 4.3, "kisiSayisi": 66765, "tur": "$2_1_BILEN"}, {"oid": "641bplhmav0fll05", "kisiBasinaDusenIkramiye": 3, "kisiSayisi": 93750, "tur": "$3_BILEN"}, {"oid": "641bplhmav0fll04", "kisiBasinaDusenIkramiye": 14.05, "kisiSayisi": 7287, "tur": "$3_1_BILEN"}, {"oid": "641bplhmav0fll03", "kisiBasinaDusenIkramiye": 22.85, "kisiSayisi": 3517, "tur": "$4_BILEN"}, {"oid": "641bplhmav0fll02", "kisiBasinaDusenIkramiye": 237.95, "kisiSayisi": 253, "tur": "$4_1_BILEN"}, {"oid": "641bplhmav0fll01", "kisiBasinaDusenIkramiye": 1881.65, "kisiSayisi": 32, "tur": "$5_BILEN"}, {"oid": "641bplhmav0fll00", "kisiBasinaDusenIkramiye": 602061.45, "kisiSayisi": 1, "tur": "$5_1_BILEN"}], "buyukIkrKazananIlIlceler": [{"il": "14", "ilView": "BOLU", "ilce": "01400", "ilceView": "MERKEZ"}], "kibrisHasilati": 16655.25, "devirTutari": 0, "kolonSayisi": 7012614, "kdv": 799749.95, "toplamHasilat": 5259460.5, "hasilat": 4459710.55, "sov": 445971.06, "ikramiyeEH": 4013739.4899999998, "buyukIkramiye": 602060.92, "haftayaDevredenTutar": 0.04}