{"oid": "64w7gqhcave03d00", "hafta": 606, "buyukIkramiyeKazananIl": "", "cekilisTarihi": "23/01/2013", "cekilisTuru": "SANS_TOPU", "rakamlar": "01#08#13#14#11#04", "rakamlarNumaraSirasi": "1 - 8 - 11 - 13 - 14 - <b>04</b>", "devretti": false, "devirSayisi": 0, "bilenKisiler": [{"oid": "64snw8hcave03d00", "kisiBasinaDusenIkramiye": 125049.7, "kisiSayisi": 5, "tur": "$5_1_BILEN"}, {"oid": "64snw8hcave03d01", "kisiBasinaDusenIkramiye": 2842.45, "kisiSayisi": 22, "tur": "$5_BILEN"}, {"oid": "64snw8hcave03d02", "kisiBasinaDusenIkramiye": 226.7, "kisiSayisi": 276, "tur": "$4_1_BILEN"}, {"oid": "64snw8hcave03d03", "kisiBasinaDusenIkramiye": 27.95, "kisiSayisi": 2989, "tur": "$4_BILEN"}, {"oid": "64snw8hcave03d04", "kisiBasinaDusenIkramiye": 16.45, "kisiSayisi": 6464, "tur": "$3_1_BILEN"}, {"oid": "64snw8hcave03d05", "kisiBasinaDusenIkramiye": 3.45, "kisiSayisi": 84077, "tur": "$3_BILEN"}, {"oid": "64snw8hcave03d06", "kisiBasinaDusenIkramiye": 4.65, "kisiSayisi": 63996, "tur": "$2_1_BILEN"}, {"oid": "64snw8hcave03d07", "kisiBasinaDusenIkramiye": 2.4, "kisiSayisi": 231786, "tur": "$1_1_BILEN"}], "buyukIkrKazananIlIlceler": [{"il": "06", "ilView": "ANKARA", "ilce": "00602", "ilceView": "\u00c7ANKAYA"}, {"il": "10", "ilView": "BALIKES\u0130R", "ilce": "01013", "ilceView": "MANYAS"}, {"il": "34", "ilView": "\u0130STANBUL", "ilce": "03409", "ilceView": "GAZ\u0130OSMANPA\u015eA"}, {"il": "34", "ilView": "\u0130STANBUL", "ilce": "03437", "ilceView": "BEYL\u0130KD\u00dcZ\u00dc"}, {"il": "35", "ilView": "\u0130ZM\u0130R", "ilce": "03524", "ilceView": "BAL\u00c7OVA"}]}