{"oid": "64jyjhi251xofw00", "hafta": 699, "buyukIkramiyeKazananIl": "", "cekilisTarihi": "05/11/2014", "cekilisTuru": "SANS_TOPU", "rakamlar": "07#21#28#02#12#07", "rakamlarNumaraSirasi": "02 - 07 - 12 - 21 - 28 - <b>07</b>", "devretti": false, "devirSayisi": 0, "bilenKisiler": [{"oid": "648ffwi251xoet07", "kisiBasinaDusenIkramiye": 2.9, "kisiSayisi": 215111, "tur": "$1_1_BILEN"}, {"oid": "648ffwi251xoet06", "kisiBasinaDusenIkramiye": 4.8, "kisiSayisi": 70182, "tur": "$2_1_BILEN"}, {"oid": "648ffwi251xoet05", "kisiBasinaDusenIkramiye": 3.85, "kisiSayisi": 85571, "tur": "$3_BILEN"}, {"oid": "648ffwi251xoet04", "kisiBasinaDusenIkramiye": 12.35, "kisiSayisi": 9559, "tur": "$3_1_BILEN"}, {"oid": "648ffwi251xoet03", "kisiBasinaDusenIkramiye": 31.2, "kisiSayisi": 3017, "tur": "$4_BILEN"}, {"oid": "648ffwi251xoet02", "kisiBasinaDusenIkramiye": 201.3, "kisiSayisi": 350, "tur": "$4_1_BILEN"}, {"oid": "648ffwi251xoet01", "kisiBasinaDusenIkramiye": 2817.35, "kisiSayisi": 25, "tur": "$5_BILEN"}, {"oid": "648ffwi251xoet00", "kisiBasinaDusenIkramiye": 176059.05, "kisiSayisi": 4, "tur": "$5_1_BILEN"}], "buyukIkrKazananIlIlceler": [{"il": "06", "ilView": "ANKARA", "ilce": "00602", "ilceView": "\u00c7ANKAYA"}, {"il": "09", "ilView": "AYDIN", "ilce": "00908", "ilceView": "NAZ\u0130LL\u0130"}, {"il": "33", "ilView": "MERS\u0130N", "ilce": "03313", "ilceView": "YEN\u0130\u015eEH\u0130R"}, {"il": "34", "ilView": "\u0130STANBUL", "ilce": "03409", "ilceView": "GAZ\u0130OSMANPA\u015eA"}], "kibrisHasilati": 21028, "devirTutari": 0, "kolonSayisi": 0, "kdv": 935196.1, "toplamHasilat": 6151758, "hasilat": 5216561.9, "sov": 521656.19, "ikramiyeEH": 4694905.71, "buyukIkramiye": 704235.86, "haftayaDevredenTutar": 0}