{"oid": "on_2006-04-03", "hafta": 191, "buyukIkramiyeKazananIl": "", "cekilisTarihi": "03/04/2006", "cekilisTuru": "ON_NUMARA", "rakamlar": "07#11#13#15#17#19#23#24#27#28#37#42#47#48#50#55#65#66#69#70#76#80", "rakamlarNumaraSirasi": "7 - 11 - 13 - 15 - 17 - 19 - 23 - 24 - 27 - 28 - 37 - 42 - 47 - 48 - 50 - 55 - 65 - 66 - 69 - 70 - 76 - 80", "devretti": true, "devirSayisi": 0, "bilenKisiler": [{"oid": "on_2006-04-03_10", "kisiBasinaDusenIkramiye": 122138.34, "kisiSayisi": 0, "tur": "$10_BILEN"}, {"oid": "on_2006-04-03_9", "kisiBasinaDusenIkramiye": 1957.35, "kisiSayisi": 52, "tur": "$9_BILEN"}, {"oid": "on_2006-04-03_8", "kisiBasinaDusenIkramiye": 93.5, "kisiSayisi": 1091, "tur": "$8_BILEN"}, {"oid": "on_2006-04-03_7", "kisiBasinaDusenIkramiye": 10.45, "kisiSayisi": 11178, "tur": "$7_BILEN"}, {"oid": "on_2006-04-03_6", "kisiBasinaDusenIkramiye": 1.55, "kisiSayisi": 68086, "tur": "$6_BILEN"}, {"oid": "on_2006-04-03_0", "kisiBasinaDusenIkramiye": 1.15, "kisiSayisi": 113274, "tur": "$HIC"}], "buyukIkrKazananIlIlceler": []}