{"oid": "on_2007-11-05", "hafta": 274, "buyukIkramiyeKazananIl": "", "cekilisTarihi": "05/11/2007", "cekilisTuru": "ON_NUMARA", "rakamlar": "03#10#13#20#21#23#25#27#32#35#37#38#46#49#52#62#65#68#70#73#74#75", "rakamlarNumaraSirasi": "3 - 10 - 13 - 20 - 21 - 23 - 25 - 27 - 32 - 35 - 37 - 38 - 46 - 49 - 52 - 62 - 65 - 68 - 70 - 73 - 74 - 75", "devretti": true, "devirSayisi": 0, "bilenKisiler": [{"oid": "on_2007-11-05_10", "kisiBasinaDusenIkramiye": 61112.8, "kisiSayisi": 5, "tur": "$10_BILEN"}, {"oid": "on_2007-11-05_9", "kisiBasinaDusenIkramiye": 1197.4, "kisiSayisi": 91, "tur": "$9_BILEN"}, {"oid": "on_2007-11-05_8", "kisiBasinaDusenIkramiye": 62.2, "kisiSayisi": 1756, "tur": "$8_BILEN"}, {"oid": "on_2007-11-05_7", "kisiBasinaDusenIkramiye": 9.4, "kisiSayisi": 16525, "tur": "$7_BILEN"}, {"oid": "on_2007-11-05_6", "kisiBasinaDusenIkramiye": 1.7, "kisiSayisi": 98454, "tur": "$6_BILEN"}, {"oid": "on_2007-11-05_0", "kisiBasinaDusenIkramiye": 1.45, "kisiSayisi": 140406, "tur": "$HIC"}], "buyukIkrKazananIlIlceler": []}