{"oid": "on_2008-12-15", "hafta": 332, "buyukIkramiyeKazananIl": "", "cekilisTarihi": "15/12/2008", "cekilisTuru": "ON_NUMARA", "rakamlar": "01#11#13#15#20#26#28#29#33#35#36#44#45#46#47#54#56#59#69#72#73#75", "rakamlarNumaraSirasi": "1 - 11 - 13 - 15 - 20 - 26 - 28 - 29 - 33 - 35 - 36 - 44 - 45 - 46 - 47 - 54 - 56 - 59 - 69 - 72 - 73 - 75", "devretti": true, "devirSayisi": 0, "bilenKisiler": [{"oid": "on_2008-12-15_10", "kisiBasinaDusenIkramiye": 94759.2, "kisiSayisi": 2, "tur": "$10_BILEN"}, {"oid": "on_2008-12-15_9", "kisiBasinaDusenIkramiye": 1302.7, "kisiSayisi": 97, "tur": "$9_BILEN"}, {"oid": "on_2008-12-15_8", "kisiBasinaDusenIkramiye": 68.45, "kisiSayisi": 1855, "tur": "$8_BILEN"}, {"oid": "on_2008-12-15_7", "kisiBasinaDusenIkramiye": 9.25, "kisiSayisi": 19389, "tur": "$7_BILEN"}, {"oid": "on_2008-12-15_6", "kisiBasinaDusenIkramiye": 1.7, "kisiSayisi": 115165, "tur": "$6_BILEN"}, {"oid": "on_2008-12-15_0", "kisiBasinaDusenIkramiye": 1.5, "kisiSayisi": 156594, "tur": "$HIC"}], "buyukIkrKazananIlIlceler": []}