{"oid": "on_2008-05-19", "hafta": 302, "buyukIkramiyeKazananIl": "", "cekilisTarihi": "19/05/2008", "cekilisTuru": "ON_NUMARA", "rakamlar": "01#07#13#15#19#32#34#36#38#40#46#51#53#54#57#63#69#72#73#75#77#79", "rakamlarNumaraSirasi": "1 - 7 - 13 - 15 - 19 - 32 - 34 - 36 - 38 - 40 - 46 - 51 - 53 - 54 - 57 - 63 - 69 - 72 - 73 - 75 - 77 - 79", "devretti": true, "devirSayisi": 0, "bilenKisiler": [{"oid": "on_2008-05-19_10", "kisiBasinaDusenIkramiye": 82335.85, "kisiSayisi": 4, "tur": "$10_BILEN"}, {"oid": "on_2008-05-19_9", "kisiBasinaDusenIkramiye": 1528.55, "kisiSayisi": 72, "tur": "$9_BILEN"}, {"oid": "on_2008-05-19_8", "kisiBasinaDusenIkramiye": 74.95, "kisiSayisi": 1474, "tur": "$8_BILEN"}, {"oid": "on_2008-05-19_7", "kisiBasinaDusenIkramiye": 11.15, "kisiSayisi": 14232, "tur": "$7_BILEN"}, {"oid": "on_2008-05-19_6", "kisiBasinaDusenIkramiye": 1.95, "kisiSayisi": 86524, "tur": "$6_BILEN"}, {"oid": "on_2008-05-19_0", "kisiBasinaDusenIkramiye": 1.3, "kisiSayisi": 156935, "tur": "$HIC"}], "buyukIkrKazananIlIlceler": []}