{"oid": "on_2009-03-30", "hafta": 347, "buyukIkramiyeKazananIl": "", "cekilisTarihi": "30/03/2009", "cekilisTuru": "ON_NUMARA", "rakamlar": "02#04#05#11#12#15#17#18#20#22#33#35#38#53#55#60#61#62#66#72#73#76", "rakamlarNumaraSirasi": "2 - 4 - 5 - 11 - 12 - 15 - 17 - 18 - 20 - 22 - 33 - 35 - 38 - 53 - 55 - 60 - 61 - 62 - 66 - 72 - 73 - 76", "devretti": true, "devirSayisi": 0, "bilenKisiler": [{"oid": "on_2009-03-30_10", "kisiBasinaDusenIkramiye": 201398.03, "kisiSayisi": 0, "tur": "$10_BILEN"}, {"oid": "on_2009-03-30_9", "kisiBasinaDusenIkramiye": 1303.85, "kisiSayisi": 103, "tur": "$9_BILEN"}, {"oid": "on_2009-03-30_8", "kisiBasinaDusenIkramiye": 70.35, "kisiSayisi": 1908, "tur": "$8_BILEN"}, {"oid": "on_2009-03-30_7", "kisiBasinaDusenIkramiye": 9.9, "kisiSayisi": 19801, "tur": "$7_BILEN"}, {"oid": "on_2009-03-30_6", "kisiBasinaDusenIkramiye": 1.7, "kisiSayisi": 119856, "tur": "$6_BILEN"}, {"oid": "on_2009-03-30_0", "kisiBasinaDusenIkramiye": 1.45, "kisiSayisi": 171825, "tur": "$HIC"}], "buyukIkrKazananIlIlceler": []}