{"oid": "on_2009-12-28", "hafta": 386, "buyukIkramiyeKazananIl": "", "cekilisTarihi": "28/12/2009", "cekilisTuru": "ON_NUMARA", "rakamlar": "03#07#09#18#20#22#24#27#33#48#50#53#59#62#64#65#68#72#73#75#76#79", "rakamlarNumaraSirasi": "3 - 7 - 9 - 18 - 20 - 22 - 24 - 27 - 33 - 48 - 50 - 53 - 59 - 62 - 64 - 65 - 68 - 72 - 73 - 75 - 76 - 79", "devretti": true, "devirSayisi": 0, "bilenKisiler": [{"oid": "on_2009-12-28_10", "kisiBasinaDusenIkramiye": 201124.3, "kisiSayisi": 1, "tur": "$10_BILEN"}, {"oid": "on_2009-12-28_9", "kisiBasinaDusenIkramiye": 1635.35, "kisiSayisi": 82, "tur": "$9_BILEN"}, {"oid": "on_2009-12-28_8", "kisiBasinaDusenIkramiye": 80.55, "kisiSayisi": 1668, "tur": "$8_BILEN"}, {"oid": "on_2009-12-28_7", "kisiBasinaDusenIkramiye": 11.75, "kisiSayisi": 16359, "tur": "$7_BILEN"}, {"oid": "on_2009-12-28_6", "kisiBasinaDusenIkramiye": 2, "kisiSayisi": 100193, "tur": "$6_BILEN"}, {"oid": "on_2009-12-28_0", "kisiBasinaDusenIkramiye": 1.25, "kisiSayisi": 204121, "tur": "$HIC"}], "buyukIkrKazananIlIlceler": []}