{"oid": "on_2012-07-02", "hafta": 517, "buyukIkramiyeKazananIl": "", "cekilisTarihi": "02/07/2012", "cekilisTuru": "ON_NUMARA", "rakamlar": "06#08#09#19#29#35#36#39#44#47#48#50#52#53#54#58#60#62#63#74#77#78", "rakamlarNumaraSirasi": "6 - 8 - 9 - 19 - 29 - 35 - 36 - 39 - 44 - 47 - 48 - 50 - 52 - 53 - 54 - 58 - 60 - 62 - 63 - 74 - 77 - 78", "devretti": false, "bilenKisiler": [{"oid": "on_2012-07-02_10", "kisiBasinaDusenIkramiye": 213091.7, "kisiSayisi": 1, "tur": "$10_BILEN"}, {"oid": "on_2012-07-02_9", "kisiBasinaDusenIkramiye": 1733.35, "kisiSayisi": 82, "tur": "$9_BILEN"}, {"oid": "on_2012-07-02_8", "kisiBasinaDusenIkramiye": 87.25, "kisiSayisi": 1631, "tur": "$8_BILEN"}, {"oid": "on_2012-07-02_7", "kisiBasinaDusenIkramiye": 16.8, "kisiSayisi": 16179, "tur": "$7_BILEN"}, {"oid": "on_2012-07-02_6", "kisiBasinaDusenIkramiye": 2.9, "kisiSayisi": 99368, "tur": "$6_BILEN"}, {"oid": "on_2012-07-02_0", "kisiBasinaDusenIkramiye": 2.35, "kisiSayisi": 154509, "tur": "$HIC"}], "buyukIkrKazananIlIlceler": [{"il": "10", "ilView": "BALIKES\u0130R", "ilce": "01007", "ilceView": "EDREM\u0130T"}]}