{"oid": "64bo58hldzwiea00", "hafta": 579, "buyukIkramiyeKazananIl": "", "cekilisTarihi": "09/09/2013", "cekilisTuru": "ON_NUMARA", "rakamlar": "66#63#08#51#12#49#72#18#39#17#52#65#67#62#57#50#61#30#55#59#20#14", "rakamlarNumaraSirasi": "08 - 12 - 14 - 17 - 18 - 20 - 30 - 39 - 49 - 50 - 51 - 52 - 55 - 57 - 59 - 61 - 62 - 63 - 65 - 66 - 67 - 72", "devretti": false, "devirSayisi": 0, "bilenKisiler": [{"oid": "64hkpuhldzwie605", "kisiBasinaDusenIkramiye": 2.25, "kisiSayisi": 184383, "tur": "$HIC"}, {"oid": "64hkpuhldzwie604", "kisiBasinaDusenIkramiye": 3.2, "kisiSayisi": 100191, "tur": "$6_BILEN"}, {"oid": "64hkpuhldzwie603", "kisiBasinaDusenIkramiye": 18.4, "kisiSayisi": 16548, "tur": "$7_BILEN"}, {"oid": "64hkpuhldzwie602", "kisiBasinaDusenIkramiye": 90.4, "kisiSayisi": 1774, "tur": "$8_BILEN"}, {"oid": "64hkpuhldzwie601", "kisiBasinaDusenIkramiye": 1721.6, "kisiSayisi": 93, "tur": "$9_BILEN"}, {"oid": "64hkpuhldzwie600", "kisiBasinaDusenIkramiye": 240081.5, "kisiSayisi": 1, "tur": "$10_BILEN"}], "buyukIkrKazananIlIlceler": [{"il": "16", "ilView": "BURSA", "ilce": "01617", "ilceView": "YILDIRIM"}], "kibrisHasilati": 12338.25, "devirTutari": 0.05, "kolonSayisi": 5592917, "kdv": 637985.52, "toplamHasilat": 4194687.75, "hasilat": 3556702.23, "sov": 355670.22, "ikramiyeEH": 3201032.01, "buyukIkramiye": 240077.4, "haftayaDevredenTutar": 0}