{"oid": "64faoeheg14s8o00", "hafta": 554, "buyukIkramiyeKazananIl": "", "cekilisTarihi": "18/03/2013", "cekilisTuru": "ON_NUMARA", "rakamlar": "30#40#67#39#74#08#07#64#59#04#23#24#27#19#73#10#76#42#55#18#50#02", "rakamlarNumaraSirasi": "2 - 4 - 7 - 8 - 10 - 18 - 19 - 23 - 24 - 27 - 30 - 39 - 40 - 42 - 50 - 55 - 59 - 64 - 67 - 73 - 74 - 76", "devretti": false, "devirSayisi": 0, "bilenKisiler": [{"oid": "643rlxheg14s8o00", "kisiBasinaDusenIkramiye": 258871.7, "kisiSayisi": 1, "tur": "$10_BILEN"}, {"oid": "643rlxheg14s8o01", "kisiBasinaDusenIkramiye": 2030.65, "kisiSayisi": 85, "tur": "$9_BILEN"}, {"oid": "643rlxheg14s8o02", "kisiBasinaDusenIkramiye": 103.2, "kisiSayisi": 1677, "tur": "$8_BILEN"}, {"oid": "643rlxheg14s8o03", "kisiBasinaDusenIkramiye": 19.15, "kisiSayisi": 17260, "tur": "$7_BILEN"}, {"oid": "643rlxheg14s8o04", "kisiBasinaDusenIkramiye": 3.1, "kisiSayisi": 110762, "tur": "$6_BILEN"}, {"oid": "643rlxheg14s8o05", "kisiBasinaDusenIkramiye": 2.25, "kisiSayisi": 198830, "tur": "$HIC"}], "buyukIkrKazananIlIlceler": [{"il": "26", "ilView": "ESK\u0130\u015eEH\u0130R", "ilce": "02613", "ilceView": "ODUNPAZARI"}]}