{"oid": "648uuxiek8kqu600", "hafta": 684, "buyukIkramiyeKazananIl": "", "cekilisTarihi": "14/09/2015", "cekilisTuru": "ON_NUMARA", "rakamlar": "62#22#31#27#24#47#35#65#68#52#10#26#66#67#13#28#33#43#58#04#75#38", "rakamlarNumaraSirasi": "04 - 10 - 13 - 22 - 24 - 26 - 27 - 28 - 31 - 33 - 35 - 38 - 43 - 47 - 52 - 58 - 62 - 65 - 66 - 67 - 68 - 75", "devretti": true, "devirSayisi": 1, "bilenKisiler": [{"oid": "645m4tiek8kqu305", "kisiBasinaDusenIkramiye": 3.3, "kisiSayisi": 138330, "tur": "$HIC"}, {"oid": "645m4tiek8kqu304", "kisiBasinaDusenIkramiye": 3.8, "kisiSayisi": 93987, "tur": "$6_BILEN"}, {"oid": "645m4tiek8kqu303", "kisiBasinaDusenIkramiye": 21.1, "kisiSayisi": 15983, "tur": "$7_BILEN"}, {"oid": "645m4tiek8kqu302", "kisiBasinaDusenIkramiye": 107.75, "kisiSayisi": 1646, "tur": "$8_BILEN"}, {"oid": "645m4tiek8kqu301", "kisiBasinaDusenIkramiye": 1610.05, "kisiSayisi": 110, "tur": "$9_BILEN"}, {"oid": "645m4tiek8kqu300", "kisiBasinaDusenIkramiye": 265652.13000000006, "kisiSayisi": 0, "tur": "$10_BILEN"}], "buyukIkrKazananIlIlceler": [], "kibrisHasilati": 13114, "devirTutari": 0.01, "kolonSayisi": 4641582, "kdv": 706037.49, "toplamHasilat": 4641582, "hasilat": 3935544.51, "sov": 393554.45, "ikramiyeEH": 3541990.0599999996, "buyukIkramiye": 265649.25, "haftayaDevredenTutar": 265652.13}