{"oid": "64zk5iil8cqzqa00", "hafta": 708, "buyukIkramiyeKazananIl": "", "cekilisTarihi": "29/02/2016", "cekilisTuru": "ON_NUMARA", "rakamlar": "61#32#40#60#18#41#72#28#35#48#37#52#50#64#08#17#42#09#03#55#02#47", "rakamlarNumaraSirasi": "02 - 03 - 08 - 09 - 17 - 18 - 28 - 32 - 35 - 37 - 40 - 41 - 42 - 47 - 48 - 50 - 52 - 55 - 60 - 61 - 64 - 72", "devretti": true, "devirSayisi": 1, "bilenKisiler": [{"oid": "64ke3gil8cqzq505", "kisiBasinaDusenIkramiye": 3.2, "kisiSayisi": 162412, "tur": "$HIC"}, {"oid": "64ke3gil8cqzq504", "kisiBasinaDusenIkramiye": 3.7, "kisiSayisi": 109246, "tur": "$6_BILEN"}, {"oid": "64ke3gil8cqzq503", "kisiBasinaDusenIkramiye": 21.45, "kisiSayisi": 18006, "tur": "$7_BILEN"}, {"oid": "64ke3gil8cqzq502", "kisiBasinaDusenIkramiye": 108.5, "kisiSayisi": 1858, "tur": "$8_BILEN"}, {"oid": "64ke3gil8cqzq501", "kisiBasinaDusenIkramiye": 2317.35, "kisiSayisi": 87, "tur": "$9_BILEN"}, {"oid": "64ke3gil8cqzq500", "kisiBasinaDusenIkramiye": 302362.1400000001, "kisiSayisi": 0, "tur": "$10_BILEN"}], "buyukIkrKazananIlIlceler": [], "kibrisHasilati": 16081, "devirTutari": 0.07, "kolonSayisi": 5282776, "kdv": 803394.15, "toplamHasilat": 5282776, "hasilat": 4479381.85, "sov": 447938.19, "ikramiyeEH": 4031443.6599999997, "buyukIkramiye": 302358.27, "haftayaDevredenTutar": 302362.14}