{"oid": "3zt6e8jksl3osu00", "hafta": 836, "buyukIkramiyeKazananIl": "", "cekilisTarihi": "13/08/2018", "cekilisTuru": "ON_NUMARA", "rakamlar": "38#75#27#69#56#03#65#37#26#05#51#55#50#14#18#31#48#58#23#15#67#76", "rakamlarNumaraSirasi": "03 - 05 - 14 - 15 - 18 - 23 - 26 - 27 - 31 - 37 - 38 - 48 - 50 - 51 - 55 - 56 - 58 - 65 - 67 - 69 - 75 - 76", "devretti": false, "devirSayisi": 0, "bilenKisiler": [{"oid": "3z8gnmjksl3osq05", "kisiBasinaDusenIkramiye": 3.2, "kisiSayisi": 171251, "tur": "$HIC"}, {"oid": "3z8gnmjksl3osq04", "kisiBasinaDusenIkramiye": 4.05, "kisiSayisi": 103578, "tur": "$6_BILEN"}, {"oid": "3z8gnmjksl3osq03", "kisiBasinaDusenIkramiye": 23.95, "kisiSayisi": 16871, "tur": "$7_BILEN"}, {"oid": "3z8gnmjksl3osq02", "kisiBasinaDusenIkramiye": 132.2, "kisiSayisi": 1603, "tur": "$8_BILEN"}, {"oid": "3z8gnmjksl3osq01", "kisiBasinaDusenIkramiye": 2070.3, "kisiSayisi": 102, "tur": "$9_BILEN"}, {"oid": "3z8gnmjksl3osq00", "kisiBasinaDusenIkramiye": 79175.35, "kisiSayisi": 4, "tur": "$10_BILEN"}], "buyukIkrKazananIlIlceler": [{"il": "07", "ilView": "ANTALYA", "ilce": "00719", "ilceView": "MURATPA\u015eA"}, {"il": "37", "ilView": "KASTAMONU", "ilce": "03700", "ilceView": "MERKEZ"}, {"il": "55", "ilView": "SAMSUN", "ilce": "05504", "ilceView": "HAVZA"}, {"il": "59", "ilView": "TEK\u0130RDA\u011e", "ilce": "05922", "ilceView": "S\u00dcLEYMANPA\u015eA"}], "kibrisHasilati": 18524, "devirTutari": 0.03, "kolonSayisi": 5533077, "kdv": 841203, "toplamHasilat": 5533077, "hasilat": 4691874, "sov": 469187.4, "ikramiyeEH": 4222686.6, "buyukIkramiye": 316701.49, "haftayaDevredenTutar": 0.17}