{"oid": "3zzbfzjiakc50x00", "hafta": 827, "buyukIkramiyeKazananIl": "", "cekilisTarihi": "11/06/2018", "cekilisTuru": "ON_NUMARA", "rakamlar": "71#80#49#28#23#57#03#54#77#18#46#78#13#75#34#41#44#36#19#08#14#63", "rakamlarNumaraSirasi": "03 - 08 - 13 - 14 - 18 - 19 - 23 - 28 - 34 - 36 - 41 - 44 - 46 - 49 - 54 - 57 - 63 - 71 - 75 - 77 - 78 - 80", "devretti": false, "devirSayisi": 0, "bilenKisiler": [{"oid": "3zil2vjiakc50s05", "kisiBasinaDusenIkramiye": 3.25, "kisiSayisi": 166558, "tur": "$HIC"}, {"oid": "3zil2vjiakc50s04", "kisiBasinaDusenIkramiye": 4.2, "kisiSayisi": 100324, "tur": "$6_BILEN"}, {"oid": "3zil2vjiakc50s03", "kisiBasinaDusenIkramiye": 24.9, "kisiSayisi": 16184, "tur": "$7_BILEN"}, {"oid": "3zil2vjiakc50s02", "kisiBasinaDusenIkramiye": 132.8, "kisiSayisi": 1586, "tur": "$8_BILEN"}, {"oid": "3zil2vjiakc50s01", "kisiBasinaDusenIkramiye": 2335.9, "kisiSayisi": 90, "tur": "$9_BILEN"}, {"oid": "3zil2vjiakc50s00", "kisiBasinaDusenIkramiye": 157633.3, "kisiSayisi": 2, "tur": "$10_BILEN"}], "buyukIkrKazananIlIlceler": [{"il": "34", "ilView": "\u0130STANBUL", "ilce": "03412", "ilceView": "\u015e\u0130\u015eL\u0130"}, {"il": "34", "ilView": "\u0130STANBUL", "ilce": "03428", "ilceView": "BAH\u00c7EL\u0130EVLER"}], "kibrisHasilati": 19719, "devirTutari": 0.01, "kolonSayisi": 5507770, "kdv": 837160.32, "toplamHasilat": 5507770, "hasilat": 4670609.68, "sov": 467060.97, "ikramiyeEH": 4203548.71, "buyukIkramiye": 315266.15, "haftayaDevredenTutar": 0.06}