{"oid": "sl_1996-12-28", "hafta": 7, "buyukIkramiyeKazananIl": "", "cekilisTarihi": "28/12/1996", "cekilisTuru": "SAYISAL_LOTO", "rakamlar": "04#08#14#24#27#36", "rakamlarNumaraSirasi": "4 - 8 - 14 - 24 - 27 - 36", "devretti": true, "devirSayisi": 0, "bilenKisiler": [{"oid": "sl_1996-12-28_6", "kisiBasinaDusenIkramiye": 39626.98, "kisiSayisi": 8, "tur": "$6_BILEN"}, {"oid": "sl_1996-12-28_5", "kisiBasinaDusenIkramiye": 50.805, "kisiSayisi": 1060, "tur": "$5_BILEN"}, {"oid": "sl_1996-12-28_4", "kisiBasinaDusenIkramiye": 1.195, "kisiSayisi": 49807, "tur": "$4_BILEN"}, {"oid": "sl_1996-12-28_3", "kisiBasinaDusenIkramiye": 0.145, "kisiSayisi": 788662, "tur": "$3_BILEN"}], "buyukIkrKazananIlIlceler": []}