{"oid": "sl_2000-06-10", "hafta": 187, "buyukIkramiyeKazananIl": "", "cekilisTarihi": "10/06/2000", "cekilisTuru": "SAYISAL_LOTO", "rakamlar": "04#10#18#21#30#36", "rakamlarNumaraSirasi": "4 - 10 - 18 - 21 - 30 - 36", "devretti": true, "devirSayisi": 0, "bilenKisiler": [{"oid": "sl_2000-06-10_6", "kisiBasinaDusenIkramiye": 276295.65, "kisiSayisi": 7, "tur": "$6_BILEN"}, {"oid": "sl_2000-06-10_5", "kisiBasinaDusenIkramiye": 687.67, "kisiSayisi": 1415, "tur": "$5_BILEN"}, {"oid": "sl_2000-06-10_4", "kisiBasinaDusenIkramiye": 6.895, "kisiSayisi": 70572, "tur": "$4_BILEN"}, {"oid": "sl_2000-06-10_3", "kisiBasinaDusenIkramiye": 0.76, "kisiSayisi": 1280170, "tur": "$3_BILEN"}], "buyukIkrKazananIlIlceler": []}