{"oid": "sl_2000-08-26", "hafta": 198, "buyukIkramiyeKazananIl": "", "cekilisTarihi": "26/08/2000", "cekilisTuru": "SAYISAL_LOTO", "rakamlar": "12#17#20#24#34#44", "rakamlarNumaraSirasi": "12 - 17 - 20 - 24 - 34 - 44", "devretti": true, "devirSayisi": 0, "bilenKisiler": [{"oid": "sl_2000-08-26_6", "kisiBasinaDusenIkramiye": 203104.3, "kisiSayisi": 2, "tur": "$6_BILEN"}, {"oid": "sl_2000-08-26_5", "kisiBasinaDusenIkramiye": 479.35, "kisiSayisi": 791, "tur": "$5_BILEN"}, {"oid": "sl_2000-08-26_4", "kisiBasinaDusenIkramiye": 5.06, "kisiSayisi": 37616, "tur": "$4_BILEN"}, {"oid": "sl_2000-08-26_3", "kisiBasinaDusenIkramiye": 0.61, "kisiSayisi": 620188, "tur": "$3_BILEN"}], "buyukIkrKazananIlIlceler": []}