{"oid": "sl_2002-08-17", "hafta": 301, "buyukIkramiyeKazananIl": "", "cekilisTarihi": "17/08/2002", "cekilisTuru": "SAYISAL_LOTO", "rakamlar": "07#23#24#35#44#45", "rakamlarNumaraSirasi": "7 - 23 - 24 - 35 - 44 - 45", "devretti": true, "devirSayisi": 0, "bilenKisiler": [{"oid": "sl_2002-08-17_6", "kisiBasinaDusenIkramiye": 647266.6, "kisiSayisi": 1, "tur": "$6_BILEN"}, {"oid": "sl_2002-08-17_5", "kisiBasinaDusenIkramiye": 1157.5, "kisiSayisi": 523, "tur": "$5_BILEN"}, {"oid": "sl_2002-08-17_4", "kisiBasinaDusenIkramiye": 12.05, "kisiSayisi": 26953, "tur": "$4_BILEN"}, {"oid": "sl_2002-08-17_3", "kisiBasinaDusenIkramiye": 1.15, "kisiSayisi": 504390, "tur": "$3_BILEN"}], "buyukIkrKazananIlIlceler": []}