{"oid": "sl_2008-05-10", "hafta": 600, "buyukIkramiyeKazananIl": "", "cekilisTarihi": "10/05/2008", "cekilisTuru": "SAYISAL_LOTO", "rakamlar": "01#06#11#21#22#34", "rakamlarNumaraSirasi": "1 - 6 - 11 - 21 - 22 - 34", "devretti": true, "devirSayisi": 0, "bilenKisiler": [{"oid": "sl_2008-05-10_6", "kisiBasinaDusenIkramiye": 877669.85, "kisiSayisi": 2, "tur": "$6_BILEN"}, {"oid": "sl_2008-05-10_5", "kisiBasinaDusenIkramiye": 862.6, "kisiSayisi": 916, "tur": "$5_BILEN"}, {"oid": "sl_2008-05-10_4", "kisiBasinaDusenIkramiye": 17.55, "kisiSayisi": 26216, "tur": "$4_BILEN"}, {"oid": "sl_2008-05-10_3", "kisiBasinaDusenIkramiye": 3.05, "kisiSayisi": 453358, "tur": "$3_BILEN"}], "buyukIkrKazananIlIlceler": []}