{"oid": "sl_2009-12-12", "hafta": 683, "buyukIkramiyeKazananIl": "", "cekilisTarihi": "12/12/2009", "cekilisTuru": "SAYISAL_LOTO", "rakamlar": "15#23#25#45#47#49", "rakamlarNumaraSirasi": "15 - 23 - 25 - 45 - 47 - 49", "devretti": true, "devirSayisi": 0, "bilenKisiler": [{"oid": "sl_2009-12-12_6", "kisiBasinaDusenIkramiye": 1492467.45, "kisiSayisi": 2, "tur": "$6_BILEN"}, {"oid": "sl_2009-12-12_5", "kisiBasinaDusenIkramiye": 2169.8, "kisiSayisi": 313, "tur": "$5_BILEN"}, {"oid": "sl_2009-12-12_4", "kisiBasinaDusenIkramiye": 22.7, "kisiSayisi": 16998, "tur": "$4_BILEN"}, {"oid": "sl_2009-12-12_3", "kisiBasinaDusenIkramiye": 3.7, "kisiSayisi": 323315, "tur": "$3_BILEN"}], "buyukIkrKazananIlIlceler": []}