{"oid": "sl_2011-03-12", "hafta": 748, "buyukIkramiyeKazananIl": "", "cekilisTarihi": "12/03/2011", "cekilisTuru": "SAYISAL_LOTO", "rakamlar": "06#11#22#24#31#32", "rakamlarNumaraSirasi": "6 - 11 - 22 - 24 - 31 - 32", "devretti": true, "devirSayisi": 0, "bilenKisiler": [{"oid": "sl_2011-03-12_6", "kisiBasinaDusenIkramiye": 697935.75, "kisiSayisi": 2, "tur": "$6_BILEN"}, {"oid": "sl_2011-03-12_5", "kisiBasinaDusenIkramiye": 1734.05, "kisiSayisi": 339, "tur": "$5_BILEN"}, {"oid": "sl_2011-03-12_4", "kisiBasinaDusenIkramiye": 24.2, "kisiSayisi": 18865, "tur": "$4_BILEN"}, {"oid": "sl_2011-03-12_3", "kisiBasinaDusenIkramiye": 3.75, "kisiSayisi": 328825, "tur": "$3_BILEN"}], "buyukIkrKazananIlIlceler": []}