{"oid": "sl_2012-10-20", "hafta": 832, "buyukIkramiyeKazananIl": "", "cekilisTarihi": "20/10/2012", "cekilisTuru": "SAYISAL_LOTO", "rakamlar": "04#13#17#36#44#46", "rakamlarNumaraSirasi": "4 - 13 - 17 - 36 - 44 - 46", "devretti": false, "bilenKisiler": [{"oid": "sl_2012-10-20_6", "kisiBasinaDusenIkramiye": 762767.4, "kisiSayisi": 2, "tur": "$6_BILEN"}, {"oid": "sl_2012-10-20_5", "kisiBasinaDusenIkramiye": 2805.3, "kisiSayisi": 229, "tur": "$5_BILEN"}, {"oid": "sl_2012-10-20_4", "kisiBasinaDusenIkramiye": 39.4, "kisiSayisi": 12269, "tur": "$4_BILEN"}, {"oid": "sl_2012-10-20_3", "kisiBasinaDusenIkramiye": 5.85, "kisiSayisi": 233024, "tur": "$3_BILEN"}], "buyukIkrKazananIlIlceler": [{"il": "35", "ilView": "\u0130ZM\u0130R", "ilce": "03526", "ilceView": "GAZ\u0130EM\u0130R"}, {"il": "80", "ilView": "OSMAN\u0130YE", "ilce": "08000", "ilceView": "MERKEZ"}]}