{"oid": "sl_2012-04-28", "hafta": 807, "buyukIkramiyeKazananIl": "", "cekilisTarihi": "28/04/2012", "cekilisTuru": "SAYISAL_LOTO", "rakamlar": "01#13#22#40#42#49", "rakamlarNumaraSirasi": "1 - 13 - 22 - 40 - 42 - 49", "devretti": false, "bilenKisiler": [{"oid": "sl_2012-04-28_6", "kisiBasinaDusenIkramiye": 742643.15, "kisiSayisi": 2, "tur": "$6_BILEN"}, {"oid": "sl_2012-04-28_5", "kisiBasinaDusenIkramiye": 2019.65, "kisiSayisi": 310, "tur": "$5_BILEN"}, {"oid": "sl_2012-04-28_4", "kisiBasinaDusenIkramiye": 23.25, "kisiSayisi": 20241, "tur": "$4_BILEN"}, {"oid": "sl_2012-04-28_3", "kisiBasinaDusenIkramiye": 5.45, "kisiSayisi": 243418, "tur": "$3_BILEN"}], "buyukIkrKazananIlIlceler": [{"il": "34", "ilView": "\u0130STANBUL", "ilce": "03403", "ilceView": "BE\u015e\u0130KTA\u015e"}, {"il": "35", "ilView": "\u0130ZM\u0130R", "ilce": "03501", "ilceView": "KAR\u015eIYAKA"}]}