{"oid": "641jsji4rczhoy00", "hafta": 948, "buyukIkramiyeKazananIl": "", "cekilisTarihi": "10/01/2015", "cekilisTuru": "SAYISAL_LOTO", "rakamlar": "02#44#29#01#16#17", "rakamlarNumaraSirasi": "01 - 02 - 16 - 17 - 29 - 44", "devretti": false, "devirSayisi": 0, "bilenKisiler": [{"oid": "64e5dgi4rczhot03", "kisiBasinaDusenIkramiye": 8.45, "kisiSayisi": 153926, "tur": "$3_BILEN"}, {"oid": "64e5dgi4rczhot02", "kisiBasinaDusenIkramiye": 60.9, "kisiSayisi": 7603, "tur": "$4_BILEN"}, {"oid": "64e5dgi4rczhot01", "kisiBasinaDusenIkramiye": 4203.25, "kisiSayisi": 146, "tur": "$5_BILEN"}, {"oid": "64e5dgi4rczhot00", "kisiBasinaDusenIkramiye": 1457098.95, "kisiSayisi": 1, "tur": "$6_BILEN"}], "buyukIkrKazananIlIlceler": [{"il": "35", "ilView": "\u0130ZM\u0130R", "ilce": "03520", "ilceView": "BUCA"}], "kibrisHasilati": 47865, "devirTutari": 0.03, "kolonSayisi": 10046219, "kdv": 1525172.64, "toplamHasilat": 10046219.0, "hasilat": 8521046.36, "sov": 852104.64, "ikramiyeEH": 7668941.72, "buyukIkramiye": 1457098.93, "haftayaDevredenTutar": 0.04}