{"oid": "64d6nbipbgwhld00", "hafta": 1022, "buyukIkramiyeKazananIl": "", "cekilisTarihi": "11/06/2016", "cekilisTuru": "SAYISAL_LOTO", "rakamlar": "37#16#14#38#26#45", "rakamlarNumaraSirasi": "14 - 16 - 26 - 37 - 38 - 45", "devretti": false, "devirSayisi": 0, "bilenKisiler": [{"oid": "64zjh7ipbgwhl903", "kisiBasinaDusenIkramiye": 7.95, "kisiSayisi": 157458, "tur": "$3_BILEN"}, {"oid": "64zjh7ipbgwhl902", "kisiBasinaDusenIkramiye": 56.3, "kisiSayisi": 7975, "tur": "$4_BILEN"}, {"oid": "64zjh7ipbgwhl901", "kisiBasinaDusenIkramiye": 4199, "kisiSayisi": 141, "tur": "$5_BILEN"}, {"oid": "64zjh7ipbgwhl900", "kisiBasinaDusenIkramiye": 702645.7, "kisiSayisi": 2, "tur": "$6_BILEN"}], "buyukIkrKazananIlIlceler": [{"il": "06", "ilView": "ANKARA", "ilce": "00623", "ilceView": "MAMAK"}, {"il": "26", "ilView": "ESK\u0130\u015eEH\u0130R", "ilce": "02613", "ilceView": "ODUNPAZARI"}], "kibrisHasilati": 47901, "devirTutari": 0, "kolonSayisi": 9688707, "kdv": 1470631.42, "toplamHasilat": 9688707, "hasilat": 8218075.58, "sov": 821807.56, "ikramiyeEH": 7396268.02, "buyukIkramiye": 1405290.92, "haftayaDevredenTutar": 0.01}