{"oid": "649rgeijhhcb3y00", "hafta": 1001, "buyukIkramiyeKazananIl": "", "cekilisTarihi": "16/01/2016", "cekilisTuru": "SAYISAL_LOTO", "rakamlar": "03#32#24#37#36#31", "rakamlarNumaraSirasi": "03 - 24 - 31 - 32 - 36 - 37", "devretti": false, "devirSayisi": 0, "bilenKisiler": [{"oid": "649rg9ijhhcb3t03", "kisiBasinaDusenIkramiye": 7.6, "kisiSayisi": 207733, "tur": "$3_BILEN"}, {"oid": "649rg9ijhhcb3t02", "kisiBasinaDusenIkramiye": 53.7, "kisiSayisi": 10381, "tur": "$4_BILEN"}, {"oid": "649rg9ijhhcb3t01", "kisiBasinaDusenIkramiye": 4400.6, "kisiSayisi": 169, "tur": "$5_BILEN"}, {"oid": "649rg9ijhhcb3t00", "kisiBasinaDusenIkramiye": 3331271, "kisiSayisi": 1, "tur": "$6_BILEN"}], "buyukIkrKazananIlIlceler": [{"il": "10", "ilView": "BALIKES\u0130R", "ilce": "01003", "ilceView": "BANDIRMA"}], "kibrisHasilati": 54829, "devirTutari": 1566151.07, "kolonSayisi": 12170489, "kdv": 1848151.53, "toplamHasilat": 12170489.0, "hasilat": 10322337.47, "sov": 1032233.75, "ikramiyeEH": 9290103.72, "buyukIkramiye": 1765119.71, "haftayaDevredenTutar": 0.03}