{"oid": "3zkd8dj37l0tcz00", "hafta": 1072, "buyukIkramiyeKazananIl": "", "cekilisTarihi": "27/05/2017", "cekilisTuru": "SAYISAL_LOTO", "rakamlar": "31#48#18#16#14#05", "rakamlarNumaraSirasi": "05 - 14 - 16 - 18 - 31 - 48", "devretti": true, "devirSayisi": 2, "bilenKisiler": [{"oid": "3ztpy5j37l0tcu02", "kisiBasinaDusenIkramiye": 10.85, "kisiSayisi": 141592, "tur": "$3_BILEN"}, {"oid": "3ztpy5j37l0tcu01", "kisiBasinaDusenIkramiye": 73.9, "kisiSayisi": 7424, "tur": "$4_BILEN"}, {"oid": "3ztpy5j37l0tcu00", "kisiBasinaDusenIkramiye": 5947.1, "kisiSayisi": 122, "tur": "$5_BILEN"}, {"oid": "3ztpy5j37l0tct00", "kisiBasinaDusenIkramiye": 3407068.1100000003, "kisiSayisi": 0, "tur": "$6_BILEN"}], "buyukIkrKazananIlIlceler": [], "kibrisHasilati": 58158, "devirTutari": 1684527.75, "kolonSayisi": 7917365, "kdv": 1802728.91, "toplamHasilat": 11876047.5, "hasilat": 10073318.59, "sov": 1007331.86, "ikramiyeEH": 9065986.73, "buyukIkramiye": 1722537.48, "haftayaDevredenTutar": 3407068.11}