{"oid": "3zvr41jafn61a200", "hafta": 1098, "buyukIkramiyeKazananIl": "", "cekilisTarihi": "25/11/2017", "cekilisTuru": "SAYISAL_LOTO", "rakamlar": "20#03#32#40#11#45", "rakamlarNumaraSirasi": "03 - 11 - 20 - 32 - 40 - 45", "devretti": true, "devirSayisi": 2, "bilenKisiler": [{"oid": "3zvr4kjafn619x03", "kisiBasinaDusenIkramiye": 10.75, "kisiSayisi": 162870, "tur": "$3_BILEN"}, {"oid": "3zvr4kjafn619x02", "kisiBasinaDusenIkramiye": 69.15, "kisiSayisi": 9089, "tur": "$4_BILEN"}, {"oid": "3zvr4kjafn619x01", "kisiBasinaDusenIkramiye": 3678.7, "kisiSayisi": 225, "tur": "$5_BILEN"}, {"oid": "3zvr4kjafn619x00", "kisiBasinaDusenIkramiye": 3801830.42, "kisiSayisi": 0, "tur": "$6_BILEN"}], "buyukIkrKazananIlIlceler": [], "kibrisHasilati": 57606, "devirTutari": 1836199.47, "kolonSayisi": 9035725, "kdv": 2058709.04, "toplamHasilat": 13553587.5, "hasilat": 11494878.46, "sov": 1149487.85, "ikramiyeEH": 10345390.610000001, "buyukIkramiye": 1965624.22, "haftayaDevredenTutar": 3801830.42}