{"oid": "3ztrpxjjrgtg1o00", "hafta": 1132, "buyukIkramiyeKazananIl": "", "cekilisTarihi": "18/07/2018", "cekilisTuru": "SAYISAL_LOTO", "rakamlar": "38#01#35#48#26#25", "rakamlarNumaraSirasi": "01 - 25 - 26 - 35 - 38 - 48", "devretti": true, "devirSayisi": 3, "bilenKisiler": [{"oid": "3zj5cljjrgtg1k03", "kisiBasinaDusenIkramiye": 12.3, "kisiSayisi": 56740, "tur": "$3_BILEN"}, {"oid": "3zj5cljjrgtg1k02", "kisiBasinaDusenIkramiye": 84.95, "kisiSayisi": 2944, "tur": "$4_BILEN"}, {"oid": "3zj5cljjrgtg1k01", "kisiBasinaDusenIkramiye": 7852.1, "kisiSayisi": 42, "tur": "$5_BILEN"}, {"oid": "3zj5cljjrgtg1k00", "kisiBasinaDusenIkramiye": 4363974.45, "kisiSayisi": 0, "tur": "$6_BILEN"}], "buyukIkrKazananIlIlceler": [], "kibrisHasilati": 30775.5, "devirTutari": 3580816.53, "kolonSayisi": 3599137, "kdv": 818836.78, "toplamHasilat": 5398705.5, "hasilat": 4579868.72, "sov": 457986.87, "ikramiyeEH": 4121881.8499999996, "buyukIkramiye": 783157.55, "haftayaDevredenTutar": 4363974.45}