{"oid": "3zjq4njo7h2ilm00", "hafta": 1164, "buyukIkramiyeKazananIl": "", "cekilisTarihi": "07/11/2018", "cekilisTuru": "SAYISAL_LOTO", "rakamlar": "28#46#23#22#17#13", "rakamlarNumaraSirasi": "13 - 17 - 22 - 23 - 28 - 46", "devretti": true, "devirSayisi": 3, "bilenKisiler": [{"oid": "3z43kzjo7h2ili03", "kisiBasinaDusenIkramiye": 11, "kisiSayisi": 88403, "tur": "$3_BILEN"}, {"oid": "3z43kzjo7h2ili02", "kisiBasinaDusenIkramiye": 75.3, "kisiSayisi": 4594, "tur": "$4_BILEN"}, {"oid": "3z43kzjo7h2ili01", "kisiBasinaDusenIkramiye": 5395.8, "kisiSayisi": 85, "tur": "$5_BILEN"}, {"oid": "3z43kzjo7h2ili00", "kisiBasinaDusenIkramiye": 3699826.5599999996, "kisiSayisi": 0, "tur": "$6_BILEN"}], "buyukIkrKazananIlIlceler": [], "kibrisHasilati": 41764.5, "devirTutari": 2610693.96, "kolonSayisi": 5005420, "kdv": 1138937.11, "toplamHasilat": 7508130, "hasilat": 6369192.89, "sov": 636919.29, "ikramiyeEH": 5732273.6, "buyukIkramiye": 1089131.98, "haftayaDevredenTutar": 3699826.56}