{"oid": "sul_2007-12-27", "hafta": 10, "buyukIkramiyeKazananIl": "", "cekilisTarihi": "27/12/2007", "cekilisTuru": "SUPER_LOTO", "rakamlar": "01#10#15#20#22#49", "rakamlarNumaraSirasi": "1 - 10 - 15 - 20 - 22 - 49", "devretti": true, "devirSayisi": 0, "bilenKisiler": [{"oid": "sul_2007-12-27_6", "kisiBasinaDusenIkramiye": 3211065.35, "kisiSayisi": 0, "tur": "$6_BILEN"}, {"oid": "sul_2007-12-27_5", "kisiBasinaDusenIkramiye": 4629.65, "kisiSayisi": 36, "tur": "$5_BILEN"}, {"oid": "sul_2007-12-27_4", "kisiBasinaDusenIkramiye": 78.45, "kisiSayisi": 2298, "tur": "$4_BILEN"}, {"oid": "sul_2007-12-27_3", "kisiBasinaDusenIkramiye": 6.65, "kisiSayisi": 44207, "tur": "$3_BILEN"}], "buyukIkrKazananIlIlceler": []}