{"oid": "sul_2008-08-14", "hafta": 43, "buyukIkramiyeKazananIl": "", "cekilisTarihi": "14/08/2008", "cekilisTuru": "SUPER_LOTO", "rakamlar": "15#17#33#47#52#54", "rakamlarNumaraSirasi": "15 - 17 - 33 - 47 - 52 - 54", "devretti": true, "devirSayisi": 0, "bilenKisiler": [{"oid": "sul_2008-08-14_6", "kisiBasinaDusenIkramiye": 865796.62, "kisiSayisi": 0, "tur": "$6_BILEN"}, {"oid": "sul_2008-08-14_5", "kisiBasinaDusenIkramiye": 5116.85, "kisiSayisi": 44, "tur": "$5_BILEN"}, {"oid": "sul_2008-08-14_4", "kisiBasinaDusenIkramiye": 83.65, "kisiSayisi": 2924, "tur": "$4_BILEN"}, {"oid": "sul_2008-08-14_3", "kisiBasinaDusenIkramiye": 6.6, "kisiSayisi": 60009, "tur": "$3_BILEN"}], "buyukIkrKazananIlIlceler": []}