{"oid": "sul_2011-08-25", "hafta": 201, "buyukIkramiyeKazananIl": "", "cekilisTarihi": "25/08/2011", "cekilisTuru": "SUPER_LOTO", "rakamlar": "14#22#25#28#47#53", "rakamlarNumaraSirasi": "14 - 22 - 25 - 28 - 47 - 53", "devretti": true, "devirSayisi": 0, "bilenKisiler": [{"oid": "sul_2011-08-25_6", "kisiBasinaDusenIkramiye": 2331465.75, "kisiSayisi": 0, "tur": "$6_BILEN"}, {"oid": "sul_2011-08-25_5", "kisiBasinaDusenIkramiye": 3625.55, "kisiSayisi": 106, "tur": "$5_BILEN"}, {"oid": "sul_2011-08-25_4", "kisiBasinaDusenIkramiye": 85.6, "kisiSayisi": 4862, "tur": "$4_BILEN"}, {"oid": "sul_2011-08-25_3", "kisiBasinaDusenIkramiye": 7.25, "kisiSayisi": 97766, "tur": "$3_BILEN"}], "buyukIkrKazananIlIlceler": []}