{"oid": "645l36hhcadkzs00", "hafta": 293, "buyukIkramiyeKazananIl": "", "cekilisTarihi": "30/05/2013", "cekilisTuru": "SUPER_LOTO", "rakamlar": "13#4#37#34#46#3", "rakamlarNumaraSirasi": "3 - 4 - 13 - 34 - 37 - 46", "devretti": false, "devirSayisi": 0, "bilenKisiler": [{"oid": "645l39hhcadkzs03", "kisiBasinaDusenIkramiye": 7.1, "kisiSayisi": 133947, "tur": "$3_BILEN"}, {"oid": "645l39hhcadkzs02", "kisiBasinaDusenIkramiye": 83.05, "kisiSayisi": 6688, "tur": "$4_BILEN"}, {"oid": "645l39hhcadkzs01", "kisiBasinaDusenIkramiye": 4183.05, "kisiSayisi": 123, "tur": "$5_BILEN"}, {"oid": "645l39hhcadkzs00", "kisiBasinaDusenIkramiye": 6617549.25, "kisiSayisi": 1, "tur": "$6_BILEN"}], "buyukIkrKazananIlIlceler": [{"il": "68", "ilView": "AKSARAY", "ilce": "06800", "ilceView": "MERKEZ"}], "kibrisHasilati": 0, "devirTutari": 0, "kolonSayisi": 0, "kdv": 0, "toplamHasilat": 0, "hasilat": 0, "sov": 0, "ikramiyeEH": 0, "buyukIkramiye": 0}