{"oid": "64v78uix0oc6ph00", "hafta": 479, "buyukIkramiyeKazananIl": "", "cekilisTarihi": "22/12/2016", "cekilisTuru": "SUPER_LOTO", "rakamlar": "54#48#19#41#51#25", "rakamlarNumaraSirasi": "19 - 25 - 41 - 48 - 51 - 54", "devretti": true, "devirSayisi": 4, "bilenKisiler": [{"oid": "64qdonix0oc6pd03", "kisiBasinaDusenIkramiye": 16.65, "kisiSayisi": 53169, "tur": "$3_BILEN"}, {"oid": "64qdonix0oc6pd02", "kisiBasinaDusenIkramiye": 205.5, "kisiSayisi": 2491, "tur": "$4_BILEN"}, {"oid": "64qdonix0oc6pd01", "kisiBasinaDusenIkramiye": 14031.9, "kisiSayisi": 34, "tur": "$5_BILEN"}, {"oid": "64qdonix0oc6pd00", "kisiBasinaDusenIkramiye": 5760560.05, "kisiSayisi": 0, "tur": "$6_BILEN"}], "buyukIkrKazananIlIlceler": [], "kibrisHasilati": 45156, "devirTutari": 4227081.01, "kolonSayisi": 4463846, "kdv": 1354963.12, "toplamHasilat": 8927692, "hasilat": 7572728.88, "sov": 757272.89, "ikramiyeEH": 6815455.99, "buyukIkramiye": 1533477.6, "haftayaDevredenTutar": 5760560.05}